<annotation>
	<folder>Main Dataset</folder>
	<filename>mono_ext1_4.jpeg</filename>
	<path>D:\Desktop\Graduation_design\windows_v1.8.1\Main Dataset\mono_ext1_4.jpeg</path>
	<source>
		<database>Unknown</database>
	</source>
	<size>
		<width>320</width>
		<height>240</height>
		<depth>3</depth>
	</size>
	<segmented>0</segmented>
	<object>
		<name>Mono</name>
		<pose>Unspecified</pose>
		<truncated>0</truncated>
		<difficult>0</difficult>
		<bndbox>
			<xmin>63</xmin>
			<ymin>20</ymin>
			<xmax>172</xmax>
			<ymax>119</ymax>
		</bndbox>
	</object>
</annotation>
